README.md
setup.cfg
setup.py
SamplePairsGaussian.egg-info/PKG-INFO
SamplePairsGaussian.egg-info/SOURCES.txt
SamplePairsGaussian.egg-info/dependency_links.txt
SamplePairsGaussian.egg-info/requires.txt
SamplePairsGaussian.egg-info/top_level.txt
examples/add_remove_move_particles.py
examples/add_remove_move_particles_multispecies.py
examples/histograms_1d.py
examples/multiple_1d.py
examples/multiple_1d_multispecies.py
examples/sample_2d.py
examples/simple.py
examples/simple_multispecies.py
samplePairsGaussian/__init__.py
samplePairsGaussian/prob_calculator.py
samplePairsGaussian/prob_calculator_multispecies.py
samplePairsGaussian/sampler.py
samplePairsGaussian/sampler_abstract_base.py
samplePairsGaussian/sampler_multispecies.py