Metadata-Version: 1.1
Name: SamplePairsGaussian
Version: 1.1
Summary: Sample pairs of particles according to a discrete Gaussian distrbution
Home-page: https://github.com/smrfeld/sample-pairs-gaussian
Author: Oliver K. Ernst
Author-email: UNKNOWN
License: GNU General Public License v3.0
Platform: UNKNOWN
Classifier: Development Status :: 5 - Production/Stable
Classifier: Intended Audience :: Developers
Classifier: Topic :: Scientific/Engineering :: Mathematics
Classifier: License :: OSI Approved :: GNU General Public License v3 (GPLv3)
Classifier: Programming Language :: Python :: 3
Classifier: Operating System :: OS Independent
